THU_News/THU_News.py
THU_News/__init__.py
THU_News-0.0.4.dist-info/LICENSE
THU_News-0.0.4.dist-info/METADATA
THU_News-0.0.4.dist-info/WHEEL
THU_News-0.0.4.dist-info/top_level.txt
THU_News-0.0.4.dist-info/RECORD
