Metadata-Version: 2.1
Name: THU-News
Version: 0.0.4
Summary: A python programm for getting gamma cross section
Home-page: https://github.com/AlbertWulf/Python-for-THU-News-title
Author: Albert_Wu
Author-email: wulf16@mails.tsinghua.edu.cn
License: UNKNOWN
Platform: UNKNOWN
Classifier: Programming Language :: Python :: 3 
Classifier: License :: OSI Approved :: MIT License
Classifier: Operating System :: OS Independent
